{"inkVersion":21,"root":[["#","^1_1_Shackled","/#","#","^scene_intro","/#","#","^captivity","/#",{"->":"INTRO"},["done",{"#n":"g-0"}],null],"done",{"INTRO":["#","^slow:300","/#","^You wake.","\n","ev",3000,{"x()":"pause","exArgs":1},"pop","/ev","\n","^The cold, hard floor pushes against your seated body. Shackles around your wrists and ankles pin you to the ground. Your mind is foggy like it has not been used for days.","\n","^Around you, three hooded figures stand, cloaked in darkness.","\n","^A rattling voice from in front breaks the silence. \"He wakes.\"","\n","^\"Does he know his name?\" asks the voice to your left.","\n","^There's a scoff on your right. \"That matters not, Truth.\"","\n","^\"Peace, Mercy. Peace,\" says the figure in front. \"You - you poor, chained creature, do you know your name?\"","\n",{"->":"CHOOSE_NAME"},null],"CHOOSE_NAME":[["ev","str","^Say nothing","/str","/ev",{"*":".^.c-0","flg":20},"ev","str","^Say your name","/str","/ev",{"*":".^.c-1","flg":20},"ev","str","^Say no","/str","/ev",{"*":".^.c-2","flg":20},{"c-0":["\n","^Figure in front: \"Silent, are you?\"","\n","^Truth: \"Perhaps, Order, he does not remember.\"","\n","^Mercy: \"Or perhaps he chooses not to.\"","\n",{"->":"INPUT_KNOW_WHO_THE_WITNESSES_ARE"},{"#f":5}],"c-1":["\n",{"->":"INPUT_NAME"},{"#f":5}],"c-2":["\n",{"->":"DOESNT_KNOW_NAME"},{"#f":5}]}],null],"INPUT_NAME":["ev",{"x()":"getPlayerInput"},"/ev",{"VAR=":"player_name","re":true},"\n","ev","str","^player.name","/str",{"VAR?":"player_name"},{"x()":"setLabel","exArgs":2},"pop","/ev","\n","^Figure in front: \"","ev",{"VAR?":"player_name"},"out","/ev","^?\"","\n","ev",300,{"x()":"pause","exArgs":1},"pop","/ev","\n","#","^slow:200","/#","^\"That's not...\"","\n","ev",500,{"x()":"pause","exArgs":1},"pop","/ev","\n","^Mercy: \"He doesn't know, Order, that's why.\"","\n","^Order: \"Unfortunate.\"","\n",{"->":"INPUT_KNOW_WHO_THE_WITNESSES_ARE"},null],"DOESNT_KNOW_NAME":[{"->":"INPUT_KNOW_WHO_THE_WITNESSES_ARE"},null],"INPUT_KNOW_WHO_THE_WITNESSES_ARE":[["^Truth: \"Do you know who we are?\"","\n","ev","str","^Say nothing","/str","/ev",{"*":".^.c-0","flg":20},"ev","str","^Say yes","/str","/ev",{"*":".^.c-1","flg":20},"ev","str","^Say no","/str","/ev",{"*":".^.c-2","flg":20},{"c-0":["\n","^Order: \"Again.\"","\n","^Truth: \"Still he does not know.\"","\n","^Mercy: \"Or perhaps he chooses not to.\"","\n","^Truth: \"I would not blame him.\"","\n","^[There is silence]","\n","ev","str","^witnesses.said.something_happened_before","/str",true,{"x()":"setFlag","exArgs":2},"pop","/ev","\n",{"->":"FINALISE_NAME"},{"#f":5}],"c-1":["\n","^Mercy: \"He lies.\"","\n","^Truth: \"You must be mistaken.\"","\n","^Order: \"We mustn't delay, either way...\"","\n","ev","str","^witnesses.said.something_happened_before","/str",true,{"x()":"setFlag","exArgs":2},"pop","/ev","\n",{"->":"FINALISE_NAME"},{"#f":5}],"c-2":["\n","^Truth: \"Perfect.\"","\n","^Mercy: \"Good.\"","\n","^[There is silence]","\n","ev",500,{"x()":"pause","exArgs":1},"pop","/ev","\n","^Judgement: \"We mustn't delay, either way...\"","\n","ev","str","^witnesses.said.maybe_something_happened_before","/str",true,{"x()":"setFlag","exArgs":2},"pop","/ev","\n",{"->":"FINALISE_NAME"},{"#f":5}]}],null],"FINALISE_NAME":["^Truth: \"The mask chose him. Yes. That is all that matters.\"","\n","^Order: \"And now, it must begin.\"","\n","^A pause.","\n","^Finally, the centre figure, Order, steps forward. He holds a black mask that blends into the darkness around.","\n","^He presses it to your face.","\n",{"->":"OSSANETH_MASK"},null],"OSSANETH_MASK":["ev","str","^Ossaneth","/str",{"x()":"playerForceMask","exArgs":1},"pop","/ev","\n","^[You cannot resist. It binds to you.]","\n","^The figures fade away, your grasp on reality rapidly vanishing.","\n","^A flat, impartial voice inside your head cuts through. It's your mask.","\n","^\"You may call me Ossaneth, the Unblinking Eye.\"","\n","^[You faint.]","\n","ev","str","^player.received_ossaneth","/str",true,{"x()":"setFlag","exArgs":2},"pop","/ev","\n","ev","str","^player.masks_count","/str",1,{"x()":"setCounter","exArgs":2},"pop","/ev","\n","ev","str","^player.scenes_count","/str",1,{"x()":"setCounter","exArgs":2},"pop","/ev","\n","ev","str","^player.talked_to_witnesses_count","/str",1,{"x()":"setCounter","exArgs":2},"pop","/ev","\n","end",null],"global decl":["ev","str","^","/str",{"VAR=":"player_name"},"/ev","end",null]}],"listDefs":{}}